groom_utils/__init__.py
groom_utils/groom_utils.py
groomhi_utils-0.1.0.dist-info/METADATA
groomhi_utils-0.1.0.dist-info/WHEEL
groomhi_utils-0.1.0.dist-info/top_level.txt
groomhi_utils-0.1.0.dist-info/RECORD
