Metadata-Version: 2.4
Name: groomhi-utils
Version: 0.1.0
Summary: Prints hello groom worlds
Author-email: aks <123456aks28@gmail.com>
License: MIT
Requires-Python: >=3.7
